Metadata-Version: 1.0
Name: Products.OFolder
Version: 2.0.1
Summary: A tiny ordered folder for Zope 2.11 (or above)
Home-page: http://www.dieter.handshake.de/pyprojects/zope
Author: Dieter Maurer
Author-email: dieter@handshake.de
License: BSD
Keywords: Zope 2,ordered,folder
Platform: UNKNOWN
Classifier: Development Status :: 5 - Production/Stable
Classifier: Intended Audience :: Developers
Classifier: License :: OSI Approved :: BSD License
Classifier: Framework :: Zope2
Classifier: Operating System :: OS Independent
Classifier: Programming Language :: Python
Classifier: Topic :: Utilities
